[
    {
        "UNITID":100706
    },
    {
        "UNITID":100812
    },
    {
        "UNITID":100858
    },
    {
        "UNITID":102234
    },
    {
        "UNITID":102553
    },
    {
        "UNITID":122436
    },
    {
        "UNITID":122755
    },
    {
        "UNITID":133951
    },
    {
        "UNITID":139861
    },
    {
        "UNITID":169983
    },
    {
        "UNITID":177418
    },
    {
        "UNITID":186399
    },
    {
        "UNITID":190044
    },
    {
        "UNITID":198695
    },
    {
        "UNITID":216010
    },
    {
        "UNITID":228723
    },
    {
        "UNITID":232982
    },
    {
        "UNITID":234915
    },
    {
        "UNITID":239105
    },
    {
        "UNITID":240462
    },
    {
        "UNITID":426314
    },
    {
        "UNITID":449339
    },
    {
        "UNITID":460349
    },
    {
        "UNITID":480569
    },
    {
        "UNITID":483124
    },
    {
        "UNITID":483595
    },
    {
        "UNITID":490133
    }
]