[
    {
        "UNITID":104151
    },
    {
        "UNITID":108232
    },
    {
        "UNITID":110370
    },
    {
        "UNITID":111081
    },
    {
        "UNITID":123952
    },
    {
        "UNITID":132657
    },
    {
        "UNITID":140951
    },
    {
        "UNITID":144740
    },
    {
        "UNITID":165334
    },
    {
        "UNITID":167358
    },
    {
        "UNITID":184694
    },
    {
        "UNITID":194578
    },
    {
        "UNITID":196194
    },
    {
        "UNITID":204796
    },
    {
        "UNITID":228246
    },
    {
        "UNITID":232186
    },
    {
        "UNITID":233921
    },
    {
        "UNITID":241216
    },
    {
        "UNITID":443410
    },
    {
        "UNITID":461148
    }
]