[
    {
        "UNITID":100858
    },
    {
        "UNITID":110468
    },
    {
        "UNITID":125231
    },
    {
        "UNITID":131469
    },
    {
        "UNITID":133881
    },
    {
        "UNITID":135081
    },
    {
        "UNITID":142832
    },
    {
        "UNITID":143978
    },
    {
        "UNITID":144740
    },
    {
        "UNITID":148487
    },
    {
        "UNITID":159647
    },
    {
        "UNITID":169248
    },
    {
        "UNITID":172699
    },
    {
        "UNITID":179159
    },
    {
        "UNITID":190150
    },
    {
        "UNITID":190576
    },
    {
        "UNITID":191649
    },
    {
        "UNITID":196060
    },
    {
        "UNITID":196468
    },
    {
        "UNITID":200800
    },
    {
        "UNITID":204857
    },
    {
        "UNITID":207971
    },
    {
        "UNITID":217882
    },
    {
        "UNITID":225511
    },
    {
        "UNITID":228723
    },
    {
        "UNITID":236577
    },
    {
        "UNITID":241331
    },
    {
        "UNITID":241410
    },
    {
        "UNITID":242653
    },
    {
        "UNITID":413413
    },
    {
        "UNITID":455664
    },
    {
        "UNITID":459745
    },
    {
        "UNITID":484613
    },
    {
        "UNITID":492607
    }
]