[
    {
        "UNITID":104179
    },
    {
        "UNITID":110538
    },
    {
        "UNITID":110556
    },
    {
        "UNITID":110565
    },
    {
        "UNITID":110574
    },
    {
        "UNITID":110583
    },
    {
        "UNITID":110592
    },
    {
        "UNITID":110608
    },
    {
        "UNITID":110617
    },
    {
        "UNITID":111948
    },
    {
        "UNITID":120883
    },
    {
        "UNITID":122409
    },
    {
        "UNITID":122597
    },
    {
        "UNITID":126614
    },
    {
        "UNITID":139931
    },
    {
        "UNITID":139940
    },
    {
        "UNITID":139959
    },
    {
        "UNITID":141574
    },
    {
        "UNITID":144892
    },
    {
        "UNITID":144962
    },
    {
        "UNITID":147703
    },
    {
        "UNITID":147767
    },
    {
        "UNITID":149222
    },
    {
        "UNITID":149772
    },
    {
        "UNITID":155399
    },
    {
        "UNITID":156125
    },
    {
        "UNITID":161253
    },
    {
        "UNITID":166869
    },
    {
        "UNITID":172644
    },
    {
        "UNITID":173920
    },
    {
        "UNITID":174066
    },
    {
        "UNITID":174233
    },
    {
        "UNITID":174783
    },
    {
        "UNITID":175856
    },
    {
        "UNITID":178615
    },
    {
        "UNITID":179159
    },
    {
        "UNITID":179557
    },
    {
        "UNITID":181215
    },
    {
        "UNITID":185590
    },
    {
        "UNITID":187444
    },
    {
        "UNITID":194310
    },
    {
        "UNITID":196088
    },
    {
        "UNITID":196149
    },
    {
        "UNITID":196176
    },
    {
        "UNITID":199157
    },
    {
        "UNITID":200004
    },
    {
        "UNITID":200253
    },
    {
        "UNITID":200280
    },
    {
        "UNITID":201441
    },
    {
        "UNITID":209551
    },
    {
        "UNITID":214777
    },
    {
        "UNITID":219471
    },
    {
        "UNITID":223232
    },
    {
        "UNITID":225511
    },
    {
        "UNITID":227331
    },
    {
        "UNITID":227368
    },
    {
        "UNITID":228459
    },
    {
        "UNITID":228705
    },
    {
        "UNITID":228778
    },
    {
        "UNITID":228787
    },
    {
        "UNITID":229337
    },
    {
        "UNITID":229814
    },
    {
        "UNITID":230728
    },
    {
        "UNITID":231174
    },
    {
        "UNITID":236948
    },
    {
        "UNITID":240189
    },
    {
        "UNITID":240268
    },
    {
        "UNITID":240471
    },
    {
        "UNITID":240480
    },
    {
        "UNITID":498571
    }
]