[
    {
        "UNITID":104151
    },
    {
        "UNITID":110635
    },
    {
        "UNITID":110662
    },
    {
        "UNITID":110705
    },
    {
        "UNITID":120883
    },
    {
        "UNITID":139940
    },
    {
        "UNITID":144740
    },
    {
        "UNITID":145637
    },
    {
        "UNITID":148487
    },
    {
        "UNITID":150136
    },
    {
        "UNITID":153658
    },
    {
        "UNITID":164076
    },
    {
        "UNITID":164988
    },
    {
        "UNITID":176965
    },
    {
        "UNITID":178059
    },
    {
        "UNITID":181464
    },
    {
        "UNITID":185129
    },
    {
        "UNITID":190150
    },
    {
        "UNITID":190664
    },
    {
        "UNITID":194091
    },
    {
        "UNITID":195809
    },
    {
        "UNITID":204796
    },
    {
        "UNITID":211440
    },
    {
        "UNITID":212054
    },
    {
        "UNITID":215062
    },
    {
        "UNITID":216339
    },
    {
        "UNITID":228787
    },
    {
        "UNITID":240444
    },
    {
        "UNITID":498562
    }
]