[
    {
        "name":"Sirenaro_1",
        "ingamename":"Ballaro"
    },
    {
        "name":"Boucharo",
        "ingamename":"Boucharo"
    },
    {
        "name":"Brumaro",
        "ingamename":"Brumaro"
    },
    {
        "name":"Chromaro",
        "ingamename":"Chromaro"
    },
    {
        "name":"Reacharo_2",
        "ingamename":"Fragaro"
    },
    {
        "name":"Grandaro",
        "ingamename":"Grandaro"
    },
    {
        "name":"Joyaro",
        "ingamename":"Joyaro"
    },
    {
        "name":"Monocaro",
        "ingamename":"Monocaro"
    },
    {
        "name":"Reacharo_1",
        "ingamename":"Nusaro"
    },
    {
        "name":"Sidaro",
        "ingamename":"Sidaro"
    },
    {
        "name":"Sirenaro_2",
        "ingamename":"Urnaro"
    },
    {
        "name":"Monoco_3",
        "ingamename":"Baguettaro"
    },
    {
        "name":"Monoco_2",
        "ingamename":"Esquiaro"
    },
    {
        "name":"Monoco_1",
        "ingamename":"Cannaro"
    },
    {
        "name":"Baguette",
        "ingamename":"Baguette"
    }
]