[
    {
        "UNITID":102614
    },
    {
        "UNITID":110404
    },
    {
        "UNITID":110662
    },
    {
        "UNITID":110680
    },
    {
        "UNITID":122409
    },
    {
        "UNITID":126614
    },
    {
        "UNITID":126775
    },
    {
        "UNITID":142115
    },
    {
        "UNITID":144050
    },
    {
        "UNITID":166683
    },
    {
        "UNITID":171128
    },
    {
        "UNITID":179159
    },
    {
        "UNITID":182290
    },
    {
        "UNITID":187967
    },
    {
        "UNITID":207500
    },
    {
        "UNITID":217156
    },
    {
        "UNITID":225511
    },
    {
        "UNITID":228246
    },
    {
        "UNITID":228723
    },
    {
        "UNITID":230764
    },
    {
        "UNITID":236948
    },
    {
        "UNITID":240444
    },
    {
        "UNITID":240727
    },
    {
        "UNITID":243744
    }
]