[
    {
        "UNITID":108232
    },
    {
        "UNITID":109651
    },
    {
        "UNITID":110714
    },
    {
        "UNITID":111081
    },
    {
        "UNITID":134237
    },
    {
        "UNITID":139755
    },
    {
        "UNITID":145813
    },
    {
        "UNITID":146719
    },
    {
        "UNITID":148496
    },
    {
        "UNITID":164748
    },
    {
        "UNITID":164988
    },
    {
        "UNITID":168421
    },
    {
        "UNITID":190150
    },
    {
        "UNITID":192819
    },
    {
        "UNITID":193900
    },
    {
        "UNITID":194310
    },
    {
        "UNITID":230764
    }
]