[
    {
        "UNITID":110097
    },
    {
        "UNITID":131283
    },
    {
        "UNITID":149514
    },
    {
        "UNITID":157748
    },
    {
        "UNITID":159948
    },
    {
        "UNITID":164924
    },
    {
        "UNITID":168740
    },
    {
        "UNITID":191241
    },
    {
        "UNITID":192040
    },
    {
        "UNITID":199759
    },
    {
        "UNITID":217749
    },
    {
        "UNITID":224305
    },
    {
        "UNITID":232557
    },
    {
        "UNITID":494597
    }
]