[
    {
        "UNITID":108232
    },
    {
        "UNITID":123961
    },
    {
        "UNITID":132903
    },
    {
        "UNITID":134130
    },
    {
        "UNITID":166027
    },
    {
        "UNITID":170976
    },
    {
        "UNITID":174127
    },
    {
        "UNITID":179566
    },
    {
        "UNITID":190150
    },
    {
        "UNITID":190567
    },
    {
        "UNITID":196413
    },
    {
        "UNITID":211440
    },
    {
        "UNITID":221661
    },
    {
        "UNITID":228787
    },
    {
        "UNITID":237011
    }
]